Workbook

Sheet 📊 Análisis Financiero
A1: SGC AGRO | ANÁLISIS FINANCIERO PARA INVERSIÓN
A2: Sistema de Gestión de Contratos Inteligente | Presentación Shark Tank
A4: 📌 SUPUESTOS DEL MODELO
A5: Parámetro | B5: Valor | C5: Notas
A6: Tasa de Descuento (WACC) | B6: 0.12 | C6: Costo promedio ponderado de capital
A7: Crecimiento Ingresos Año 1→5 | B7: 0.05 | C7: Incremento anual en suscripciones
A8: Contratos gestionados (Año 1) | B8: 150 | C8: Contratos del Ministerio en cartera
A9: Precio suscripción SaaS/año | B9: 5400000 | C9: COP por entidad / año
A10: Tasa de retención clientes | B10: 0.9 | C10: % clientes que renuevan anualmente
A11: Impuesto de renta (Colombia) | B11: 0.35 | C11: Tarifa general Ley 2277 de 2022
A13: 💰 ESTRUCTURA DE INVERSIÓN (CapEx Año 0)
A14: Componente | B14: Monto (COP) | C14: % | D14: Justificación
A15: Desarrollo plataforma web (Frontend) | B15: 24000000 | C15: =B15/SUM(B15:B20) -> 0.32085561 | D15: Interfaz de carga y dashboard de contratos
A16: Infraestructura n8n + Base de Datos | B16: 18000000 | C16: =B16/SUM(B15:B20) -> 0.24064171 | D16: Servidor cloud, licencias, configuración
A17: Integración IA / NLP (embeddings) | B17: 12000000 | C17: =B17/SUM(B15:B20) -> 0.16042781 | D17: Motor de consultas semánticas
A18: Seguridad & Cumplimiento (ISO 27001) | B18: 8000000 | C18: =B18/SUM(B15:B20) -> 0.10695187 | D18: Encriptación, auditoría, certificación
A19: Capacitación & Change Management | B19: 6000000 | C19: =B19/SUM(B15:B20) -> 0.080213904 | D19: Entrenamiento equipo Ministerio
A20: Contingencia (10%) | B20: 6800000 | C20: =B20/SUM(B15:B20) -> 0.090909091 | D20: Reserva para imprevistos del proyecto
A21: INVERSIÓN TOTAL REQUERIDA | B21: =SUM(B15:B20) -> 74800000 | C21: 100%
A23: 📈 PROYECCIÓN FINANCIERA A 5 AÑOS (COP)
A24: Concepto | B24: Año 0 | C24: Año 1 | D24: Año 2 | E24: Año 3 | F24: Año 4 | G24: Año 5
A25: Ingresos por Suscripciones | B25: 0 | C25: =B8*B9 -> 810000000 | D25: =C25*(1+B7) -> 850500000 | E25: =D25*(1+B7) -> 893025000 | F25: =E25*(1+B7) -> 937676250 | G25: =F25*(1+B7) -> 9.8456006e+08
A26: Costos Operativos (OpEx) | B26: 0 | C26: =B26*(1+B7) -> 0 | D26: =C26*(1+B7) -> 0 | E26: =D26*(1+B7) -> 0 | F26: =E26*(1+B7) -> 0 | G26: =F26*(1+B7) -> 0
A27: Inversión Inicial (CapEx) | B27: =-B21 -> -74800000 | C27: - | D27: - | E27: - | F27: - | G27: 0
A28: EBITDA | B28: =B25+B26 -> 0 | C28: =C25+C26 -> 810000000 | D28: =D25+D26 -> 850500000 | E28: =E25+E26 -> 893025000 | F28: =F25+F26 -> 937676250 | G28: =G25+G26 -> 9.8456006e+08
A29: Impuesto de Renta (35%) | B29: =IF(B28>0,-B28*B11,0) -> 0 | C29: =IF(C28>0,-C28*B11,0) -> -283500000 | D29: =IF(D28>0,-D28*B11,0) -> -297675000 | E29: =IF(E28>0,-E28*B11,0) -> -312558750 | F29: =IF(F28>0,-F28*B11,0) -> -3.2818669e+08 | G29: =IF(G28>0,-G28*B11,0) -> -3.4459602e+08
A30: Flujo de Caja Libre (FCF) | B30: =-B21 -> -74800000 | C30: =C28+C29 -> 526500000 | D30: =D28+D29 -> 552825000 | E30: =E28+E29 -> 580466250 | F30: =F28+F29 -> 6.0948956e+08 | G30: =G28+G29 -> 6.3996404e+08
A32: 🎯 MÉTRICAS CLAVE DE DECISIÓN
A33: VPN (Valor Presente Neto) | B33: =IFERROR(NPV(B6,C30:G30)+B30,0) -> 1.9996368e+09 | C33: VPN > 0 → El proyecto crea valor. Inversión recomendada.
A34: TIR (Tasa Interna de Retorno) | B34: =IFERROR(IRR(B30:G30),0) -> 7.0885106 | C34: TIR > WACC (12%) → El proyecto supera el costo del capital.
A35: Período de Recuperación (Payback) | B35: =IFERROR(ABS(B30)/AVERAGE(C30:G30),0) -> 0.1285557 | C35: Tiempo estimado para recuperar la inversión inicial.
A36: ROI (Retorno sobre la Inversión) | B36: =IFERROR((B33-ABS(B30))/ABS(B30),0) -> 25.733113 | C36: % de retorno sobre cada peso invertido (valor presente).
A37: Margen EBITDA (Año 5) | B37: =IFERROR(G28/G25,0) -> 1 | C37: Eficiencia operativa proyectada al quinto año.
A39: 🦈 PROPUESTA PARA EL TIBURÓN
A40: Buscamos | B40: ="$" & TEXT(B21,"#,##0") & " COP en capital semilla" -> $74,800,000 COP en capital semilla | C40: Inversión para desarrollo e implementación del MVP
A41: Equity ofrecido | B41: 20% | C41: Participación accionaria para el/los inversor(es)
A42: Valoración implícita | B42: =B21/0.2 -> 374000000 | C42: Valuación pre-money del proyecto SGC Agro
A43: Mercado objetivo | B43: Entidades públicas Col. | C43: Ministerios, alcaldías, gobernaciones (~1,200 entidades)
A44: Diferenciador clave | B44: IA + n8n + NLP | C44: Único sistema RAG especializado en contratos públicos
A46: ⚡ Azul = inputs modificables | Negro = fórmulas | Fuente: Documento de proyecto SGC Agro – Ministerio de Agricultura

Sheet 📉 Dashboard Visual
A1: SGC AGRO | DASHBOARD EJECUTIVO
A2: Resumen visual para presentación Shark Tank
A4: 📊 INDICADORES CLAVE
A5: VPN del Proyecto | D5: TIR Esperada
A6: ='📊 Análisis Financiero'!B33 -> 1.9996368e+09 | D6: ='📊 Análisis Financiero'!B34 -> 7.0885106
A9: Payback | D9: ROI Total
A10: ='📊 Análisis Financiero'!B35 -> 0.1285557 | D10: ='📊 Análisis Financiero'!B36 -> 25.733113
A13: Inversión Req. | D13: Margen EBITDA Año 5
A14: ='📊 Análisis Financiero'!B21 -> 74800000 | D14: ='📊 Análisis Financiero'!B37 -> 1
A18: 💵 FLUJOS DE CAJA RESUMIDOS
A19: Concepto | B19: Año 0 | C19: Año 1 | D19: Año 2 | E19: Año 3 | F19: Año 4 | G19: Año 5
A20: Ingresos | B20: ='📊 Análisis Financiero'!B25 -> 0 | C20: ='📊 Análisis Financiero'!C25 -> 810000000 | D20: ='📊 Análisis Financiero'!D25 -> 850500000 | E20: ='📊 Análisis Financiero'!E25 -> 893025000 | F20: ='📊 Análisis Financiero'!F25 -> 937676250 | G20: ='📊 Análisis Financiero'!G25 -> 9.8456006e+08
A21: OpEx | B21: ='📊 Análisis Financiero'!B26 -> 0 | C21: ='📊 Análisis Financiero'!C26 -> 0 | D21: ='📊 Análisis Financiero'!D26 -> 0 | E21: ='📊 Análisis Financiero'!E26 -> 0 | F21: ='📊 Análisis Financiero'!F26 -> 0 | G21: ='📊 Análisis Financiero'!G26 -> 0
A22: EBITDA | B22: ='📊 Análisis Financiero'!B28 -> 0 | C22: ='📊 Análisis Financiero'!C28 -> 810000000 | D22: ='📊 Análisis Financiero'!D28 -> 850500000 | E22: ='📊 Análisis Financiero'!E28 -> 893025000 | F22: ='📊 Análisis Financiero'!F28 -> 937676250 | G22: ='📊 Análisis Financiero'!G28 -> 9.8456006e+08
A23: Flujo de Caja Libre | B23: ='📊 Análisis Financiero'!B30 -> -74800000 | C23: ='📊 Análisis Financiero'!C30 -> 526500000 | D23: ='📊 Análisis Financiero'!D30 -> 552825000 | E23: ='📊 Análisis Financiero'!E30 -> 580466250 | F23: ='📊 Análisis Financiero'!F30 -> 6.0948956e+08 | G23: ='📊 Análisis Financiero'!G30 -> 6.3996404e+08
A48: ⚡ IMPACTO OPERACIONAL: AS-IS vs TO-BE
A49: Dimensión | B49: AS-IS (Excel Manual) | D49: TO-BE (SGC Agro IA) | F49: Mejora
A50: Registro de contrato | B50: 20-40 min / manual | D50: < 2 min / automático | F50: ↓ 95% tiempo
A51: Búsqueda de cláusulas | B51: 15-30 min búsqueda | D51: < 10 seg (NLP) | F51: ↓ 99% tiempo
A52: Alertas de vencimiento | B52: Revisión humana ad-hoc | D52: Automática (30 días) | F52: 100% cobertura
A53: Errores de datos | B53: Frecuentes (Excel libre) | D53: Mínimos (BD protegida) | F53: ↓ 95% errores
A54: Costo por contrato | B54: ~$180,000 COP/hora | D54: ~$36,000 COP/hora | F54: ↓ 80% costo
A56: ⚡ Dashboard vinculado dinámicamente con la hoja de análisis | Modifica los supuestos en azul para ver el impacto en tiempo real
